cyberfusion/Nodechup/CLI.py
cyberfusion/Nodechup/__init__.py
cyberfusion/Nodechup/nodejs.py
cyberfusion/Nodechup/utilities.py
python3_cyberfusion_nodechup-1.4.dist-info/METADATA
python3_cyberfusion_nodechup-1.4.dist-info/WHEEL
python3_cyberfusion_nodechup-1.4.dist-info/entry_points.txt
python3_cyberfusion_nodechup-1.4.dist-info/top_level.txt
python3_cyberfusion_nodechup-1.4.dist-info/RECORD
