Metadata-Version: 2.4
Name: python3-cyberfusion-nodechup
Version: 1.4
Summary: Use nodechup to install multiple Node.js versions.
Author-email: Cyberfusion <support@cyberfusion.io>
Project-URL: Source, https://github.com/CyberfusionIO/python3-cyberfusion-nodechup
Requires-Dist: docopt==0.6.2
Requires-Dist: schema==0.7.8
Requires-Dist: requests==2.32.5
